pybgl/.gitignore
pybgl/__init__.py
pybgl/aggregated_visitor.py
pybgl/algebra.py
pybgl/automaton.py
pybgl/automaton_copy.py
pybgl/bk_tree.py
pybgl/breadth_first_search.py
pybgl/color.py
pybgl/cut.py
pybgl/damerau_levenshtein_distance.py
pybgl/depth_first_search.py
pybgl/deterministic_inclusion.py
pybgl/deterministic_intersection.py
pybgl/deterministic_union.py
pybgl/digital_sequence.py
pybgl/dijkstra_shortest_paths.py
pybgl/graph.py
pybgl/graph_copy.py
pybgl/graph_dp.py
pybgl/graph_extract.py
pybgl/graph_traversal.py
pybgl/graph_view.py
pybgl/graphviz.py
pybgl/graphviz_impl.py
pybgl/heap.py
pybgl/hopcroft_minimize.py
pybgl/html.py
pybgl/incidence_automaton.py
pybgl/incidence_graph.py
pybgl/incidence_node_automaton.py
pybgl/ipynb.py
pybgl/lcs_distance.py
pybgl/levenshtein_distance.py
pybgl/moore_determination.py
pybgl/nfa.py
pybgl/node_automaton.py
pybgl/parallel_breadth_first_search.py
pybgl/product_mixin.py
pybgl/property_map.py
pybgl/prune_incidence_automaton.py
pybgl/regexp.py
pybgl/reverse.py
pybgl/revuz_minimize.py
pybgl/shunting_yard_postfix.py
pybgl/singleton.py
pybgl/strong_components.py
pybgl/suffix_trie.py
pybgl/thompson_compile_nfa.py
pybgl/tokenize.py
pybgl/topological_sort.py
pybgl/trie.py
pybgl/trie_matching.py
pybgl-0.11.2.dist-info/WHEEL
pybgl-0.11.2.dist-info/METADATA
pybgl-0.11.2.dist-info/LICENSE
pybgl-0.11.2.dist-info/RECORD
