Metadata-Version: 2.1
Name: pybgl
Version: 0.11.2
Summary: PyBGL is a pure Python graph library inspited from the BGL (Boost Graph Library). It gathers algorithms from the graph theory, language theory and dynamic programming background.
License: BSD-3 license
Author: Marc-Olivier Buob
Author-email: marc-olivier.buob@nokia-bell-labs.com
Requires-Python: >=3.8,<4.0
Classifier: License :: Other/Proprietary License
Classifier: Programming Language :: Python :: 3
Classifier: Programming Language :: Python :: 3.8
Classifier: Programming Language :: Python :: 3.9
Classifier: Programming Language :: Python :: 3.10
Classifier: Programming Language :: Python :: 3.11
Requires-Dist: ipython (>=8.10.0)
